randomgroups/__init__.py
randomgroups/_version.py
randomgroups/algorithm.py
randomgroups/create_matching.py
randomgroups/io.py
randomgroups-0.0.4.dist-info/LICENSE
randomgroups-0.0.4.dist-info/METADATA
randomgroups-0.0.4.dist-info/WHEEL
randomgroups-0.0.4.dist-info/top_level.txt
randomgroups-0.0.4.dist-info/RECORD
