Metadata-Version: 2.1
Name: randomgroups
Version: 0.0.4
Summary: Algorithm to create recurring random groups
Home-page: https://github.com/timmens/random-grouping
Author: Tim Mensinger
Author-email: mensingertim@gmail.com
License: MIT
Classifier: License :: OSI Approved :: MIT License
Classifier: Operating System :: MacOS :: MacOS X
Classifier: Operating System :: Microsoft :: Windows
Classifier: Operating System :: POSIX
Classifier: Programming Language :: Python :: 3
Classifier: Programming Language :: Python :: 3 :: Only
Requires-Python: >=3.8
License-File: LICENSE
Requires-Dist: click
Requires-Dist: numpy (>=1.17.0)
Requires-Dist: openpyxl
Requires-Dist: pandas
